dlght/__init__.py
dlght/decorators/singleton.py
dlght/dgx/__init__.py
dlght/dgx/dgx.py
dlght/ffile/ffile.py
dlght/preset/__init__.py
dlght/preset/preset.py
dlght/preset/softwares.py
dlght-2.0.28.dist-info/WHEEL
dlght-2.0.28.dist-info/entry_points.txt
dlght-2.0.28.dist-info/METADATA
dlght-2.0.28.dist-info/RECORD
