Metadata-Version: 2.3
Name: dlght
Version: 2.0.28
Summary: 适合中国宝宝体质的GITHUB下载器
Author: lipanpan
Author-email: lipanpan <lipanpanmail@163.com>
Requires-Dist: fire>=0.7.1
Requires-Dist: prompt-toolkit>=3.0.52
Requires-Dist: requests>=2.32.5
Requires-Dist: toml>=0.10.2
Requires-Dist: pyperclip>=1.9.0
Requires-Dist: gitpython>=3.1.46
Requires-Python: >=3.13
